{"id":"d5676dcf-9cd1-4dfd-9349-99a562eef360","revision":0,"last_node_id":19,"last_link_id":19,"nodes":[{"id":3,"type":"ADE_AnimateDiffLoaderGen1","pos":[-11.92859172821045,131.57681274414062],"size":[315,242],"flags":{},"order":4,"mode":0,"inputs":[{"localized_name":"model","name":"model","type":"MODEL","link":1},{"localized_name":"context_options","name":"context_options","shape":7,"type":"CONTEXT_OPTIONS","link":null},{"localized_name":"motion_lora","name":"motion_lora","shape":7,"type":"MOTION_LORA","link":null},{"localized_name":"ad_settings","name":"ad_settings","shape":7,"type":"AD_SETTINGS","link":null},{"localized_name":"ad_keyframes","name":"ad_keyframes","shape":7,"type":"AD_KEYFRAMES","link":null},{"localized_name":"sample_settings","name":"sample_settings","shape":7,"type":"SAMPLE_SETTINGS","link":null},{"localized_name":"scale_multival","name":"scale_multival","shape":7,"type":"MULTIVAL","link":null},{"localized_name":"effect_multival","name":"effect_multival","shape":7,"type":"MULTIVAL","link":null},{"localized_name":"per_block","name":"per_block","shape":7,"type":"PER_BLOCK","link":null},{"localized_name":"model_name","name":"model_name","type":"COMBO","widget":{"name":"model_name"},"link":null},{"localized_name":"beta_schedule","name":"beta_schedule","type":"COMBO","widget":{"name":"beta_schedule"},"link":null}],"outputs":[{"localized_name":"MODEL","name":"MODEL","type":"MODEL","links":[2]}],"properties":{"cnr_id":"comfyui-animatediff-evolved","ver":"90fb1331201a4b29488089e4fbffc0d82cc6d0a9","Node name for S&R":"ADE_AnimateDiffLoaderGen1"},"widgets_values":["mm_sd15_v3.safetensors","autoselect"]},{"id":17,"type":"VAEDecode","pos":[1086.9716796875,466.7466735839844],"size":[212.60000610351562,106.5],"flags":{},"order":11,"mode":0,"inputs":[{"localized_name":"samples","name":"samples","type":"LATENT","link":16},{"localized_name":"vae","name":"vae","type":"VAE","link":8}],"outputs":[{"localized_name":"IMAGE","name":"IMAGE","type":"IMAGE","links":[17]}],"properties":{"cnr_id":"comfy-core","ver":"0.3.60","Node name for S&R":"VAEDecode"},"widgets_values":[]},{"id":15,"type":"EmptyLatentImage","pos":[1025.3712158203125,253.3466796875],"size":[270,106],"flags":{},"order":0,"mode":0,"inputs":[{"localized_name":"width","name":"width","type":"INT","widget":{"name":"width"},"link":null},{"localized_name":"height","name":"height","type":"INT","widget":{"name":"height"},"link":null},{"localized_name":"batch_size","name":"batch_size","type":"INT","widget":{"name":"batch_size"},"link":null}],"outputs":[{"localized_name":"LATENT","name":"LATENT","type":"LATENT","links":[13]}],"properties":{"cnr_id":"comfy-core","ver":"0.3.60","Node name for S&R":"EmptyLatentImage"},"widgets_values":[512,512,16]},{"id":8,"type":"CheckpointLoaderSimple","pos":[-2.248692750930786,-73.13313293457031],"size":[270,98],"flags":{},"order":1,"mode":0,"inputs":[{"localized_name":"ckpt_name","name":"ckpt_name","type":"COMBO","widget":{"name":"ckpt_name"},"link":null}],"outputs":[{"localized_name":"MODEL","name":"MODEL","type":"MODEL","links":[1]},{"localized_name":"CLIP","name":"CLIP","type":"CLIP","links":[5]},{"localized_name":"VAE","name":"VAE","type":"VAE","links":[8]}],"properties":{"cnr_id":"comfy-core","ver":"0.3.60","Node name for S&R":"CheckpointLoaderSimple"},"widgets_values":["v15PrunedEmaonly_v15PrunedEmaonly.safetensors"]},{"id":14,"type":"ControlNetLoader","pos":[-0.928810715675354,440.346923828125],"size":[270,58],"flags":{},"order":2,"mode":0,"inputs":[{"localized_name":"control_net_name","name":"control_net_name","type":"COMBO","widget":{"name":"control_net_name"},"link":null}],"outputs":[{"localized_name":"CONTROL_NET","name":"CONTROL_NET","type":"CONTROL_NET","links":[3]}],"properties":{"cnr_id":"comfy-core","ver":"0.3.60","Node name for S&R":"ControlNetLoader"},"widgets_values":["diffusion_pytorch_model.safetensors"]},{"id":12,"type":"CLIPTextEncode","pos":[344.4713439941406,198.34689331054688],"size":[210.25,147.1999969482422],"flags":{},"order":8,"mode":0,"inputs":[{"localized_name":"clip","name":"clip","type":"CLIP","link":7},{"localized_name":"text","name":"text","type":"STRING","widget":{"name":"text"},"link":null}],"outputs":[{"localized_name":"CONDITIONING","name":"CONDITIONING","type":"CONDITIONING","links":[12]}],"properties":{"cnr_id":"comfy-core","ver":"0.3.60","Node name for S&R":"CLIPTextEncode"},"widgets_values":[""],"color":"#322","bgcolor":"#533"},{"id":16,"type":"ControlNetApplyAdvanced","pos":[712.1339111328125,379.5790100097656],"size":[270,186],"flags":{},"order":9,"mode":0,"inputs":[{"localized_name":"positive","name":"positive","type":"CONDITIONING","link":11},{"localized_name":"negative","name":"negative","type":"CONDITIONING","link":12},{"localized_name":"control_net","name":"control_net","type":"CONTROL_NET","link":3},{"localized_name":"image","name":"image","type":"IMAGE","link":19},{"localized_name":"vae","name":"vae","shape":7,"type":"VAE","link":null},{"localized_name":"strength","name":"strength","type":"FLOAT","widget":{"name":"strength"},"link":null},{"localized_name":"start_percent","name":"start_percent","type":"FLOAT","widget":{"name":"start_percent"},"link":null},{"localized_name":"end_percent","name":"end_percent","type":"FLOAT","widget":{"name":"end_percent"},"link":null}],"outputs":[{"localized_name":"positive","name":"positive","type":"CONDITIONING","links":[14]},{"localized_name":"negative","name":"negative","type":"CONDITIONING","links":[15]}],"properties":{"cnr_id":"comfy-core","ver":"0.3.60","Node name for S&R":"ControlNetApplyAdvanced"},"widgets_values":[0.95,0,1]},{"id":6,"type":"VHS_VideoCombine","pos":[1411.14111328125,60.626834869384766],"size":[214.76666259765625,446.76666259765625],"flags":{},"order":12,"mode":0,"inputs":[{"localized_name":"images","name":"images","type":"IMAGE","link":17},{"localized_name":"audio","name":"audio","shape":7,"type":"AUDIO","link":null},{"localized_name":"meta_batch","name":"meta_batch","shape":7,"type":"VHS_BatchManager","link":null},{"localized_name":"vae","name":"vae","shape":7,"type":"VAE","link":null},{"localized_name":"frame_rate","name":"frame_rate","type":"FLOAT","widget":{"name":"frame_rate"},"link":null},{"localized_name":"loop_count","name":"loop_count","type":"INT","widget":{"name":"loop_count"},"link":null},{"localized_name":"filename_prefix","name":"filename_prefix","type":"STRING","widget":{"name":"filename_prefix"},"link":null},{"localized_name":"format","name":"format","type":"COMBO","widget":{"name":"format"},"link":null},{"localized_name":"pingpong","name":"pingpong","type":"BOOLEAN","widget":{"name":"pingpong"},"link":null},{"localized_name":"save_output","name":"save_output","type":"BOOLEAN","widget":{"name":"save_output"},"link":null}],"outputs":[{"localized_name":"Filenames","name":"Filenames","type":"VHS_FILENAMES","links":null}],"properties":{"cnr_id":"comfyui-videohelpersuite","ver":"1.7.7","Node name for S&R":"VHS_VideoCombine"},"widgets_values":{"frame_rate":12,"loop_count":0,"filename_prefix":"AnimateDiff","format":"image/gif","pingpong":false,"save_output":true,"videopreview":{"hidden":false,"paused":false,"params":{"filename":"AnimateDiff_00052.gif","subfolder":"","type":"output","format":"image/gif","frame_rate":12,"workflow":"AnimateDiff_00052.png","fullpath":"/home/dpc/usr/bin/ComfyUI/output/AnimateDiff_00052.gif"}}}},{"id":10,"type":"CLIPSetLastLayer","pos":[0.9415081739425659,571.6868896484375],"size":[251.3000030517578,59.099998474121094],"flags":{},"order":5,"mode":0,"inputs":[{"localized_name":"clip","name":"clip","type":"CLIP","link":5},{"localized_name":"stop_at_clip_layer","name":"stop_at_clip_layer","type":"INT","widget":{"name":"stop_at_clip_layer"},"link":null}],"outputs":[{"localized_name":"CLIP","name":"CLIP","type":"CLIP","links":[6,7]}],"properties":{"cnr_id":"comfy-core","ver":"0.3.60","Node name for S&R":"CLIPSetLastLayer"},"widgets_values":[-3]},{"id":19,"type":"Canny","pos":[1039.15966796875,28.90055274963379],"size":[270,82],"flags":{},"order":6,"mode":0,"inputs":[{"localized_name":"image","name":"image","type":"IMAGE","link":18},{"localized_name":"low_threshold","name":"low_threshold","type":"FLOAT","widget":{"name":"low_threshold"},"link":null},{"localized_name":"high_threshold","name":"high_threshold","type":"FLOAT","widget":{"name":"high_threshold"},"link":null}],"outputs":[{"localized_name":"IMAGE","name":"IMAGE","type":"IMAGE","links":[19]}],"properties":{"cnr_id":"comfy-core","ver":"0.3.60","Node name for S&R":"Canny"},"widgets_values":[0.3,0.5]},{"id":5,"type":"KSampler","pos":[363.5411071777344,421.61053466796875],"size":[270,262],"flags":{},"order":10,"mode":0,"inputs":[{"localized_name":"model","name":"model","type":"MODEL","link":2},{"localized_name":"positive","name":"positive","type":"CONDITIONING","link":14},{"localized_name":"negative","name":"negative","type":"CONDITIONING","link":15},{"localized_name":"latent_image","name":"latent_image","type":"LATENT","link":13},{"localized_name":"seed","name":"seed","type":"INT","widget":{"name":"seed"},"link":null},{"localized_name":"steps","name":"steps","type":"INT","widget":{"name":"steps"},"link":null},{"localized_name":"cfg","name":"cfg","type":"FLOAT","widget":{"name":"cfg"},"link":null},{"localized_name":"sampler_name","name":"sampler_name","type":"COMBO","widget":{"name":"sampler_name"},"link":null},{"localized_name":"scheduler","name":"scheduler","type":"COMBO","widget":{"name":"scheduler"},"link":null},{"localized_name":"denoise","name":"denoise","type":"FLOAT","widget":{"name":"denoise"},"link":null}],"outputs":[{"localized_name":"LATENT","name":"LATENT","type":"LATENT","links":[16]}],"properties":{"cnr_id":"comfy-core","ver":"0.3.60","Node name for S&R":"KSampler"},"widgets_values":[1023087451286190,"randomize",20,8,"euler","simple",0.9]},{"id":13,"type":"LoadImage","pos":[660.188720703125,-54.11761474609375],"size":[274,314],"flags":{},"order":3,"mode":0,"inputs":[{"localized_name":"image","name":"image","type":"COMBO","widget":{"name":"image"},"link":null},{"localized_name":"choose file to upload","name":"upload","type":"IMAGEUPLOAD","widget":{"name":"upload"},"link":null}],"outputs":[{"localized_name":"IMAGE","name":"IMAGE","type":"IMAGE","links":[18]},{"localized_name":"MASK","name":"MASK","type":"MASK","links":null}],"properties":{"cnr_id":"comfy-core","ver":"0.3.60","Node name for S&R":"LoadImage"},"widgets_values":["ComfyUI_00088_.png","image"]},{"id":11,"type":"CLIPTextEncode","pos":[340.0714416503906,-17.253171920776367],"size":[226.20001220703125,145],"flags":{},"order":7,"mode":0,"inputs":[{"localized_name":"clip","name":"clip","type":"CLIP","link":6},{"localized_name":"text","name":"text","type":"STRING","widget":{"name":"text"},"link":null}],"outputs":[{"localized_name":"CONDITIONING","name":"CONDITIONING","type":"CONDITIONING","links":[11]}],"properties":{"cnr_id":"comfy-core","ver":"0.3.60","Node name for S&R":"CLIPTextEncode"},"widgets_values":["let the character join a fight"],"color":"#232","bgcolor":"#353"}],"links":[[1,8,0,3,0,"MODEL"],[2,3,0,5,0,"MODEL"],[3,14,0,16,2,"CONTROL_NET"],[5,8,1,10,0,"CLIP"],[6,10,0,11,0,"CLIP"],[7,10,0,12,0,"CLIP"],[8,8,2,17,1,"VAE"],[11,11,0,16,0,"CONDITIONING"],[12,12,0,16,1,"CONDITIONING"],[13,15,0,5,3,"LATENT"],[14,16,0,5,1,"CONDITIONING"],[15,16,1,5,2,"CONDITIONING"],[16,5,0,17,0,"LATENT"],[17,17,0,6,0,"IMAGE"],[18,13,0,19,0,"IMAGE"],[19,19,0,16,3,"IMAGE"]],"groups":[],"config":{},"extra":{"ds":{"scale":0.7513148009015777,"offset":[533.7364500528929,283.9628556504128]}},"version":0.4}